ccfrobot/__init__.py
ccfrobot/__main__.py
ccfrobot/api/__init__.py
ccfrobot/api/cli/__init__.py
ccfrobot/api/cli/__myproto__/__init__.py
ccfrobot/api/cli/__myproto__/fpredicate/__init__.py
ccfrobot/api/cli/__myproto__/fpredicate/fobject.py
ccfrobot/api/cli/__myproto__/fpredicate/object.py
ccfrobot/api/cli/__myproto__/predicate/__init__.py
ccfrobot/api/cli/__myproto__/predicate/object.py
ccfrobot/api/cli/subparsers/__init__.py
ccfrobot/api/cli/subparsers/create.py
ccfrobot/api/cli/subparsers/describe.py
ccfrobot/api/cli/subparsers/execute.py
ccfrobot/api/cli/subparsers/hash.py
ccfrobot/api/cli/subparsers/list.py
ccfrobot/api/cli/subparsers/validate.py
ccfrobot/api/http/__init__.py
ccfrobot/api/http/automation.py
ccfrobot/api/http/framework.py
ccfrobot/api/http/lobster_custom.py
ccfrobot/schema/__init__.py
ccfrobot/skills/__init__.py
ccfrobot/skills/create.py
ccfrobot/skills/describe.py
ccfrobot/skills/execute.py
ccfrobot/skills/hash.py
ccfrobot/skills/host.py
ccfrobot/skills/list.py
ccfrobot/skills/validate.py
ccfrobot-0.2.6.dist-info/LICENSE
ccfrobot-0.2.6.dist-info/METADATA
ccfrobot-0.2.6.dist-info/WHEEL
ccfrobot-0.2.6.dist-info/top_level.txt
ccfrobot-0.2.6.dist-info/zip-safe
ccfrobot-0.2.6.dist-info/RECORD
