Metadata-Version: 2.1
Name: ccfrobot
Version: 0.2.6
Summary: Cloud Code Framework Robot
Home-page: https://bitbucket.org/inno-on/ccfrobot
Author: Tiara Rodney - Innovations ON GmbH
Author-email: t.rodney@inno-on.de
License: UNKNOWN
Project-URL: Bug Tracker, https://bitbucket.org/inno-on/ccfrobot/issues
Platform: UNKNOWN
Requires-Python: >=3.6
License-File: LICENSE
Requires-Dist: jsonschema (==3.2.0)
Requires-Dist: PyYAML (==5.4.1)
Requires-Dist: pyhcl (==0.4.4)
